visionai_data_format/__init__.py
visionai_data_format/convert_dataset.py
visionai_data_format/vai_to_bdd.py
visionai_data_format/vai_to_bdd_v2.py
visionai_data_format/converters/__init__.py
visionai_data_format/converters/base.py
visionai_data_format/converters/bdd_to_vai.py
visionai_data_format/converters/coco_to_vai.py
visionai_data_format/converters/kitti_to_vai.py
visionai_data_format/converters/vai_to_coco.py
visionai_data_format/converters/vai_to_yolo.py
visionai_data_format/converters/yolo_to_vai.py
visionai_data_format/exceptions/__init__.py
visionai_data_format/exceptions/constants.py
visionai_data_format/exceptions/error_messages.py
visionai_data_format/exceptions/visionai.py
visionai_data_format/schemas/__init__.py
visionai_data_format/schemas/bdd_schema.py
visionai_data_format/schemas/coco_schema.py
visionai_data_format/schemas/common.py
visionai_data_format/schemas/ontology.py
visionai_data_format/schemas/visionai_schema.py
visionai_data_format/schemas/utils/__init__.py
visionai_data_format/schemas/utils/validators.py
visionai_data_format/utils/__init__.py
visionai_data_format/utils/calculation.py
visionai_data_format/utils/checker.py
visionai_data_format/utils/classes.py
visionai_data_format/utils/common.py
visionai_data_format/utils/converter.py
visionai_data_format/utils/resize.py
visionai_data_format/utils/validator.py
visionai_data_format-2.0.0.dist-info/METADATA
visionai_data_format-2.0.0.dist-info/WHEEL
visionai_data_format-2.0.0.dist-info/top_level.txt
visionai_data_format-2.0.0.dist-info/RECORD
