Metadata-Version: 2.2
Name: visionai-data-format
Version: 2.0.0
Summary: converter tool for visionai format
Home-page: 
Author: LinkerVision
Requires-Python: >=3.8, <4
Requires-Dist: pydantic==2.*
Requires-Dist: pillow
Provides-Extra: test
Requires-Dist: pytest; extra == "test"
Requires-Dist: mock; extra == "test"
Requires-Dist: pre-commit; extra == "test"
Dynamic: author
Dynamic: description
Dynamic: description-content-type
Dynamic: provides-extra
Dynamic: requires-dist
Dynamic: requires-python
Dynamic: summary
